edx_recommendations/__init__.py
edx_recommendations/apps.py
edx_recommendations/toggles.py
edx_recommendations-1.0.6.dist-info/LICENSE.txt
edx_recommendations-1.0.6.dist-info/METADATA
edx_recommendations-1.0.6.dist-info/WHEEL
edx_recommendations-1.0.6.dist-info/entry_points.txt
edx_recommendations-1.0.6.dist-info/top_level.txt
edx_recommendations-1.0.6.dist-info/RECORD
