Metadata-Version: 2.1
Name: edx-recommendations
Version: 1.0.6
Summary: A edx-platform plugin for learner recommendations.
Home-page: https://github.com/openedx/edx-recommendations
Author: edX
Author-email: oscm@edx.org
License: AGPL 3.0
Keywords: Python edx
Classifier: Development Status :: 3 - Alpha
Classifier: Framework :: Django
Classifier: Framework :: Django :: 3.2
Classifier: Framework :: Django :: 4.2
Classifier: Intended Audience :: Developers
Classifier: License :: OSI Approved :: GNU Affero General Public License v3 or later (AGPLv3+)
Classifier: Natural Language :: English
Classifier: Programming Language :: Python :: 3
Classifier: Programming Language :: Python :: 3.8
Requires-Python: >=3.8
License-File: LICENSE.txt
Requires-Dist: Django
Requires-Dist: django-ipware
Requires-Dist: djangorestframework
Requires-Dist: edx-django-utils
Requires-Dist: edx-drf-extensions
Requires-Dist: edx-toggles
